README.md
license.txt
setup.py
batch_checkpoint_merger/__init__.py
batch_checkpoint_merger/__main__.py
batch_checkpoint_merger/main.py
batch_checkpoint_merger.egg-info/PKG-INFO
batch_checkpoint_merger.egg-info/SOURCES.txt
batch_checkpoint_merger.egg-info/dependency_links.txt
batch_checkpoint_merger.egg-info/requires.txt
batch_checkpoint_merger.egg-info/top_level.txt